mongodb_api/__init__.py
mongodb_api/mongodb_api.py
mongodb_api-0.0.1.dist-info/LICENSE
mongodb_api-0.0.1.dist-info/METADATA
mongodb_api-0.0.1.dist-info/WHEEL
mongodb_api-0.0.1.dist-info/top_level.txt
mongodb_api-0.0.1.dist-info/RECORD
